belfry_python_anvil/__init__.py
belfry_python_anvil/api.py
belfry_python_anvil/api_resources/__init__.py
belfry_python_anvil/api_resources/base.py
belfry_python_anvil/api_resources/mutations/__init__.py
belfry_python_anvil/api_resources/mutations/base.py
belfry_python_anvil/api_resources/mutations/create_etch_packet.py
belfry_python_anvil/api_resources/mutations/forge_submit.py
belfry_python_anvil/api_resources/mutations/generate_etch_signing_url.py
belfry_python_anvil/api_resources/mutations/helpers.py
belfry_python_anvil/api_resources/payload.py
belfry_python_anvil/api_resources/requests.py
belfry_python_anvil/cli.py
belfry_python_anvil/constants.py
belfry_python_anvil/exceptions.py
belfry_python_anvil/http.py
belfry_python_anvil/py.typed
belfry_python_anvil/tests/__init__.py
belfry_python_anvil/tests/conftest.py
belfry_python_anvil/tests/payloads.py
belfry_python_anvil/tests/test_api.py
belfry_python_anvil/tests/test_cli.py
belfry_python_anvil/tests/test_http.py
belfry_python_anvil/tests/test_utils.py
belfry_python_anvil/utils.py
belfry_python_anvil-4.0.1.dist-info/LICENSE.md
belfry_python_anvil-4.0.1.dist-info/METADATA
belfry_python_anvil-4.0.1.dist-info/WHEEL
belfry_python_anvil-4.0.1.dist-info/entry_points.txt
belfry_python_anvil-4.0.1.dist-info/RECORD
