Metadata-Version: 2.1
Name: belfry_python_anvil
Version: 4.0.1
Summary: Fork of Anvil API
Home-page: https://www.useanvil.com/
License: MIT
Keywords: anvil,api,pdf,signing
Author: Alex Tulenko
Author-email: alex@belfrysoftware.com
Requires-Python: >=3.8.0,<3.13
Classifier: Development Status :: 3 - Alpha
Classifier: License :: OSI Approved :: MIT License
Classifier: Natural Language :: English
Classifier: Operating System :: OS Independent
Classifier: Programming Language :: Python
Classifier: Programming Language :: Python :: 3
Classifier: Programming Language :: Python :: 3.8
Classifier: Programming Language :: Python :: 3.9
Classifier: Programming Language :: Python :: 3.10
Classifier: Programming Language :: Python :: 3.11
Classifier: Programming Language :: Python :: 3.12
Classifier: Programming Language :: Python :: 3.7
Classifier: Topic :: Software Development :: Libraries :: Python Modules
Requires-Dist: click (>=8.0,<9.0)
Requires-Dist: gql[requests] (==3.6.0b1)
Requires-Dist: pydantic (>=2.6.1,<3.0.0)
Requires-Dist: ratelimit (>=2.2.1,<3.0.0)
Requires-Dist: requests (>=2.28.2,<3.0.0)
Requires-Dist: tabulate (>=0.9.0,<0.10.0)
Requires-Dist: urllib3 (<2)
Project-URL: Documentation, https://github.com/BelfrySoftware/python-anvil
Project-URL: Repository, https://github.com/BelfrySoftware/python-anvil
